Metadata-Version: 1.1
Name: django-image-optimizer
Version: 1.0.1
Summary: Django Image Optimizer (Compressor)
Home-page: https://github.com/agusmakmun/django-image-optimizer
Author: Agus Makmun (Summon Agus)
Author-email: summon.agus@gmail.com
License: MIT
Download-URL: https://github.com/agusmakmun/django-image-optimizer/tarball/v1.0.1
Keywords: image optimizer,django image optimizer,image optimizer
Platform: UNKNOWN
Classifier: Development Status :: 5 - Production/Stable
Classifier: Environment :: Web Environment
Classifier: Framework :: Django
Classifier: Framework :: Django :: 1.8
Classifier: Framework :: Django :: 1.9
Classifier: Framework :: Django :: 1.10
Classifier: Framework :: Django :: 1.11
Classifier: Framework :: Django :: 2.0
Classifier: Intended Audience :: Developers
Classifier: Operating System :: OS Independent
Classifier: Programming Language :: Python
Classifier: Programming Language :: Python :: 2.7
Classifier: Programming Language :: Python :: 3.3
Classifier: Programming Language :: Python :: 3.5
Classifier: Programming Language :: Python :: 3.7
Classifier: Topic :: Software Development :: Libraries :: Python Modules
Classifier: License :: OSI Approved :: MIT License
